{
  "session_id": "0a5603f1-76d6-4a4a-b57c-e9bd62e3c49d",
  "project_path": "/home/herbert",
  "start_time": "2026-03-03T17:49:10.475Z",
  "duration_minutes": 56,
  "user_message_count": 16,
  "assistant_message_count": 249,
  "tool_counts": {
    "Bash": 94,
    "TaskCreate": 19,
    "Glob": 3,
    "TaskUpdate": 19,
    "Write": 4,
    "Edit": 10,
    "Read": 1,
    "AskUserQuestion": 4,
    "TaskOutput": 1
  },
  "languages": {
    "TypeScript": 2,
    "JSON": 3,
    "Python": 8
  },
  "git_commits": 0,
  "git_pushes": 0,
  "input_tokens": 322,
  "output_tokens": 34892,
  "first_prompt": "I want to hear and talk to you, what is with the voice output happening here",
  "user_interruptions": 0,
  "user_response_times": [
    72.674,
    87.966,
    35.739,
    15.405,
    24.681,
    25.033,
    33.196,
    55.846,
    48.882,
    124.416,
    20.475,
    87.164,
    87.164
  ],
  "tool_errors": 9,
  "tool_error_categories": {
    "Command Failed": 7,
    "Edit Failed": 1,
    "Other": 1
  },
  "uses_task_agent": false,
  "uses_mcp": false,
  "uses_web_search": false,
  "uses_web_fetch": false,
  "lines_added": 553,
  "lines_removed": 68,
  "files_modified": 5,
  "message_hours": [
    18,
    18,
    18,
    19,
    19,
    19,
    19,
    19,
    19,
    19,
    19,
    19,
    19,
    19,
    19,
    19
  ],
  "user_message_timestamps": [
    "2026-03-03T17:49:12.332Z",
    "2026-03-03T17:49:10.317Z",
    "2026-03-03T17:58:30.454Z",
    "2026-03-03T18:01:09.472Z",
    "2026-03-03T18:04:26.676Z",
    "2026-03-03T18:05:28.277Z",
    "2026-03-03T18:06:58.225Z",
    "2026-03-03T18:07:47.807Z",
    "2026-03-03T18:09:44.564Z",
    "2026-03-03T18:11:54.343Z",
    "2026-03-03T18:13:30.033Z",
    "2026-03-03T18:15:19.904Z",
    "2026-03-03T18:39:30.955Z",
    "2026-03-03T18:41:55.214Z",
    "2026-03-03T18:44:17.352Z",
    "2026-03-03T18:44:17.352Z"
  ]
}